django_unmigrated_sql-0.3.0.dist-info/licenses/LICENSE
management/__init__.py
management/commands/__init__.py
management/commands/unmigrated-sql.py
django_unmigrated_sql-0.3.0.dist-info/METADATA
django_unmigrated_sql-0.3.0.dist-info/WHEEL
django_unmigrated_sql-0.3.0.dist-info/top_level.txt
django_unmigrated_sql-0.3.0.dist-info/RECORD
